cloud/download-nda-data
cloud/downloadcmd-auther
cloud/gmscalc-HCPYA
cloud/list-rapidtide-relevant-images
cloud/mount-and-run
cloud/rapidtide-HCPYA
cloud/rapidtide-cloud-test
cloud/simple-cp-test
rapidtide/Colortables.py
rapidtide/OrthoImageItem.py
rapidtide/RapidtideDataset.py
rapidtide/__init__.py
rapidtide/_version.py
rapidtide/calccoherence.py
rapidtide/calcnullsimfunc.py
rapidtide/calcsimfunc.py
rapidtide/correlate.py
rapidtide/decorators.py
rapidtide/dlfilter.py
rapidtide/dlfiltertorch.py
rapidtide/externaltools.py
rapidtide/fMRIData_class.py
rapidtide/ffttools.py
rapidtide/filter.py
rapidtide/fit.py
rapidtide/genericmultiproc.py
rapidtide/happy_supportfuncs.py
rapidtide/helper_classes.py
rapidtide/io.py
rapidtide/linfitfiltpass.py
rapidtide/makelaggedtcs.py
rapidtide/maskutil.py
rapidtide/miscmath.py
rapidtide/multiproc.py
rapidtide/patchmatch.py
rapidtide/peakeval.py
rapidtide/ppgproc.py
rapidtide/qualitycheck.py
rapidtide/refinedelay.py
rapidtide/refineregressor.py
rapidtide/resample.py
rapidtide/simFuncClasses.py
rapidtide/simfuncfit.py
rapidtide/stats.py
rapidtide/tidepoolTemplate.py
rapidtide/tidepoolTemplate.ui
rapidtide/tidepoolTemplate_alt.py
rapidtide/tidepoolTemplate_alt.ui
rapidtide/tidepoolTemplate_alt_qt6.py
rapidtide/tidepoolTemplate_big.py
rapidtide/tidepoolTemplate_big.ui
rapidtide/tidepoolTemplate_big_qt6.py
rapidtide/tidepoolTemplate_qt6.py
rapidtide/util.py
rapidtide/voxelData.py
rapidtide/wiener.py
rapidtide/wiener2.py
rapidtide/data/examples/src/installtestdata
rapidtide/data/examples/src/testLD
rapidtide/data/examples/src/test_findmaxlag.py
rapidtide/data/examples/src/test_io
rapidtide/data/examples/src/test_mlregressallt.py
rapidtide/data/examples/src/test_rapidtidecompare
rapidtide/data/examples/src/testalign
rapidtide/data/examples/src/testatlasaverage
rapidtide/data/examples/src/testboth
rapidtide/data/examples/src/testcifti
rapidtide/data/examples/src/testcomplex
rapidtide/data/examples/src/testdecomp
rapidtide-3.1.3.dist-info/licenses/LICENSE
rapidtide-3.1.3.dist-info/METADATA
rapidtide-3.1.3.dist-info/WHEEL
rapidtide-3.1.3.dist-info/entry_points.txt
rapidtide-3.1.3.dist-info/top_level.txt
rapidtide-3.1.3.dist-info/RECORD
