Metadata-Version: 2.4
Name: rapidtide
Version: 3.1.3
Summary: Tools for performing correlation analysis on fMRI data.
Author: Taylor Salo, Daniel M. Drucker, Ph.D., Jeffrey N Stout, Yaroslav O. Halchenko, Derek Monroe
Author-email: "Blaise deB. Frederick" <blaise.frederick@gmail.com>
License: Apache Software License
Project-URL: Homepage, https://github.com/bbfrederick/rapidtide
Project-URL: Bug Tracker, https://github.com/bbfrederick/rapidtide/issues
Project-URL: Repository, https://github.com/bbfrederick/rapidtide.git
Project-URL: Documentation, https://rapidtide.readthedocs.io
Project-URL: Changelog, https://github.com/bbfrederick/rapidtide/blob/main/CHANGELOG.md
Keywords: fMRI,correlation,RIPTiDe,noise
Classifier: Operating System :: OS Independent
Classifier: Development Status :: 5 - Production/Stable
Classifier: Intended Audience :: Science/Research
Classifier: Topic :: Scientific/Engineering :: Image Recognition
Classifier: License :: OSI Approved :: Apache Software License
Classifier: Programming Language :: Python :: 3.10
Classifier: Programming Language :: Python :: 3.11
Classifier: Programming Language :: Python :: 3.12
Classifier: Programming Language :: Python :: 3.13
Classifier: Programming Language :: Python :: 3.14
Requires-Python: >=3.10
License-File: LICENSE
Requires-Dist: numpy
Requires-Dist: scipy
Requires-Dist: pandas
Requires-Dist: pyarrow
Requires-Dist: scikit-image
Requires-Dist: scikit-learn
Requires-Dist: nibabel
Requires-Dist: nilearn
Requires-Dist: matplotlib
Requires-Dist: pyqtgraph
Requires-Dist: pyqt6-sip
Requires-Dist: pyqt6
Requires-Dist: requests
Requires-Dist: statsmodels
Requires-Dist: pywavelets
Requires-Dist: torch
Requires-Dist: tqdm
Requires-Dist: versioneer
Provides-Extra: tf
Requires-Dist: tensorflow>=2.18.0; extra == "tf"
Requires-Dist: tf-keras>=2.18.0; extra == "tf"
Provides-Extra: test
Requires-Dist: codecov; extra == "test"
Requires-Dist: coverage; extra == "test"
Requires-Dist: coveralls; extra == "test"
Requires-Dist: flake8-black; extra == "test"
Requires-Dist: pytest; extra == "test"
Requires-Dist: pytest-cov; extra == "test"
Provides-Extra: doc
Requires-Dist: sphinx; extra == "doc"
Requires-Dist: sphinx_rtd_theme; extra == "doc"
Requires-Dist: sphinx-argparse; extra == "doc"
Requires-Dist: sphinx-gallery; extra == "doc"
Requires-Dist: myst-parser; extra == "doc"
Requires-Dist: numpydoc; extra == "doc"
Requires-Dist: sphinxcontrib-bibtex; extra == "doc"
Requires-Dist: tomlkit; extra == "doc"
Dynamic: license-file
